percheron/__init__.py
percheron/__main__.py
percheron/cli.py
percheron/config.py
percheron-0.0.4.dist-info/LICENSE
percheron-0.0.4.dist-info/METADATA
percheron-0.0.4.dist-info/WHEEL
percheron-0.0.4.dist-info/entry_points.txt
percheron-0.0.4.dist-info/top_level.txt
percheron-0.0.4.dist-info/RECORD
