Metadata-Version: 2.1
Name: percheron
Version: 0.0.4
Home-page: https://github.com/glasnt/percheron
Author: Katie McLaughlin
License: Apache License, Version 2.0
Project-URL: Issues, https://github.com/glasnt/percheron/issues
Project-URL: CI, https://github.com/glasnt/percheron/actions
Project-URL: Changelog, https://github.com/glasnt/percheron/releases
Requires-Python: >=3.7
License-File: LICENSE
Requires-Dist: click
Requires-Dist: GitPython
Requires-Dist: requests
Requires-Dist: requests-cache[all]
Requires-Dist: rich-click
Requires-Dist: tqdm
Requires-Dist: nltk
Requires-Dist: python-dotenv
Requires-Dist: datasette
Requires-Dist: sqlite-utils
Provides-Extra: test
Requires-Dist: pytest ; extra == 'test'
